fin_nln/__init__.py
fin_nln/.ipynb_checkpoints/__init__-checkpoint.py
fin_nln/multivar/__init__.py
fin_nln/multivar/tests.py
fin_nln/multivar/visuals.py
fin_nln/univar/__init__.py
fin_nln/univar/tests.py
fin_nln/univar/visuals.py
fin_nln/univar/.ipynb_checkpoints/__init__-checkpoint.py
fin_nln/univar/.ipynb_checkpoints/tests-checkpoint.py
fin_nln/univar/.ipynb_checkpoints/visuals-checkpoint.py
fin_nln-0.1.1.dist-info/licenses/LICENSE
tests/__init__.py
tests/test_integration.py
tests/test_multivariate.py
tests/test_univariate.py
fin_nln-0.1.1.dist-info/METADATA
fin_nln-0.1.1.dist-info/WHEEL
fin_nln-0.1.1.dist-info/top_level.txt
fin_nln-0.1.1.dist-info/RECORD
