Metadata-Version: 2.4
Name: fin_nln
Version: 0.1.1
Summary: Comprehensive statistical testing suite for financial time series nonlinearity detection
Home-page: https://github.com/Ross-Ede/fin_nln
Author: Ross Ede
Author-email: Ross Ede <your.email@example.com>
License: MIT
Project-URL: Homepage, https://github.com/Ross-Ede/fin_nln
Project-URL: Bug Reports, https://github.com/Ross-Ede/fin_nln/issues
Project-URL: Source, https://github.com/Ross-Ede/fin_nln
Keywords: finance,time-series,nonlinearity,econometrics,statistics
Classifier: Development Status :: 3 - Alpha
Classifier: Intended Audience :: Financial and Insurance Industry
Classifier: Intended Audience :: Science/Research
Classifier: Topic :: Office/Business :: Financial
Classifier: Topic :: Scientific/Engineering :: Mathematics
Classifier: License :: OSI Approved :: MIT License
Classifier: Programming Language :: Python :: 3
Classifier: Programming Language :: Python :: 3.8
Classifier: Programming Language :: Python :: 3.9
Classifier: Programming Language :: Python :: 3.10
Classifier: Programming Language :: Python :: 3.11
Classifier: Programming Language :: Python :: 3.12
Requires-Python: >=3.8
License-File: LICENSE
Requires-Dist: numpy>=1.21.0
Requires-Dist: pandas>=1.3.0
Requires-Dist: scipy>=1.7.0
Requires-Dist: statsmodels>=0.13.0
Requires-Dist: yfinance>=0.2.0
Requires-Dist: nolds>=0.5.2
Requires-Dist: arch>=5.0.0
Requires-Dist: scikit-learn>=1.0.0
Provides-Extra: dev
Requires-Dist: pytest>=7.0.0; extra == "dev"
Requires-Dist: pytest-cov>=4.0.0; extra == "dev"
Requires-Dist: black>=22.0.0; extra == "dev"
Requires-Dist: flake8>=5.0.0; extra == "dev"
Requires-Dist: sphinx>=5.0.0; extra == "dev"
Provides-Extra: plotting
Requires-Dist: matplotlib>=3.5.0; extra == "plotting"
Requires-Dist: seaborn>=0.11.0; extra == "plotting"
Dynamic: author
Dynamic: home-page
Dynamic: license-file
Dynamic: requires-python
